testless_autocomplete/__init__.py
testless_autocomplete/src/AutoCompleteAPI.py
testless_autocomplete/src/__init__.py
testless_autocomplete/src/model.py
testless_autocomplete/src/preprocessing.py
testless_autocomplete-0.0.109.dist-info/METADATA
testless_autocomplete-0.0.109.dist-info/WHEEL
testless_autocomplete-0.0.109.dist-info/top_level.txt
testless_autocomplete-0.0.109.dist-info/RECORD
