Metadata-Version: 2.1
Name: testless-autocomplete
Version: 0.0.109
Summary: Auto Complete Package
Author: TestLess
License: MIT
Classifier: License :: OSI Approved :: MIT License
Classifier: Programming Language :: Python :: 3.10
Classifier: Operating System :: OS Independent
Requires-Dist: bson (>=0.5.10)
Provides-Extra: dev
Requires-Dist: pytest (>=7.0) ; extra == 'dev'
Requires-Dist: twine (>=4.0.2) ; extra == 'dev'
